forAlex/__init__.py
forAlex/main.py
forAlex-1.0.0.dist-info/METADATA
forAlex-1.0.0.dist-info/WHEEL
forAlex-1.0.0.dist-info/entry_points.txt
forAlex-1.0.0.dist-info/top_level.txt
forAlex-1.0.0.dist-info/RECORD
