Metadata-Version: 2.1
Name: forAlex
Version: 1.0.0
Summary: Happy Birthday Alex
Home-page: UNKNOWN
Author: TakeruIto
License: UNKNOWN
Platform: UNKNOWN
Classifier: Programming Language :: Python :: 3.7
